sirocco/__init__.py
sirocco/core.py
sirocco/parsing/__init__.py
sirocco/parsing/_utils.py
sirocco/parsing/_yaml_data_models.py
sirocco-0.0.0.dev0.dist-info/METADATA
sirocco-0.0.0.dev0.dist-info/WHEEL
sirocco-0.0.0.dev0.dist-info/RECORD
