Metadata-Version: 2.3
Name: sirocco
Version: 0.0.0.dev0
Summary: A library for creating weather and climate workflows.
Project-URL: Repository, https://github.com/C2SM/Sirocco.git
Project-URL: Changelog, https://github.com/C2SM/Sirocco/blob/main/CHANGELOG.md
Author-email: Matthieu Leclair <matthieu.leclair@env.ethz.ch>, Julian Geiger <julian.geiger@psi.ch>, Alexander Goscinski <alexander.goscinski@psi.ch>
Keywords:  icon,aiida,aiida-workgraph,workflow
Classifier: Development Status :: 1 - Planning
Classifier: Intended Audience :: Science/Research
Classifier: Operating System :: POSIX :: Linux
Classifier: Programming Language :: Python
Classifier: Programming Language :: Python :: 3.12
Classifier: Topic :: Scientific/Engineering
Classifier: Topic :: Scientific/Engineering :: Atmospheric Science
Requires-Python: >=3.12
Requires-Dist: aiida-core>=2.5
Requires-Dist: isoduration
Requires-Dist: pydantic
Requires-Dist: pydantic-yaml
